CHANGELOG.md
entente/__init__.py
entente/cli.py
entente/composite.py
entente/equality.py
entente/landmarks/__init__.py
entente/landmarks/landmark_composite_recipe.py
entente/landmarks/landmark_compositor.py
entente/landmarks/landmarker.py
entente/landmarks/serialization.py
entente/landmarks/symmetrize_landmarks.py
entente/path_transfer.py
entente/restore_correspondence.py
entente/rigid_transform.py
entente/shuffle.py
entente/surface_regressor.py
entente/symmetry.py
entente/testing.py
entente-2.2.2.dist-info/LICENSE
entente-2.2.2.dist-info/WHEEL
entente-2.2.2.dist-info/METADATA
entente-2.2.2.dist-info/RECORD
